cerbo/DL.py
cerbo/ML.py
cerbo/__init__.py
cerbo/preprocessing.py
cerbo-0.3.3.dist-info/AUTHORS
cerbo-0.3.3.dist-info/LICENSE
cerbo-0.3.3.dist-info/METADATA
cerbo-0.3.3.dist-info/WHEEL
cerbo-0.3.3.dist-info/top_level.txt
cerbo-0.3.3.dist-info/RECORD
