Metadata-Version: 2.1
Name: cerbo
Version: 0.3.3
Summary: Perform Efficient ML/DL Modelling
Home-page: https://github.com/StartOnAI/Cerbo
Author: StartOnAI
Author-email: startonaicom@gmail.com
License: UNKNOWN
Platform: UNKNOWN
Classifier: Programming Language :: Python :: 3
Classifier: License :: OSI Approved :: MIT License
Classifier: Operating System :: OS Independent
Requires-Python: >=3.6
License-File: LICENSE
License-File: AUTHORS
